proteopy/__init__.py
proteopy/ann/__init__.py
proteopy/ann/base_anndata.py
proteopy/ann/proteins.py
proteopy/datasets/__init__.py
proteopy/datasets/karayel_2020.py
proteopy/download/__init__.py
proteopy/download/contaminants.py
proteopy/get/__init__.py
proteopy/get/proteoforms.py
proteopy/get/stat_tests.py
proteopy/pl/__init__.py
proteopy/pl/clustering.py
proteopy/pl/copf.py
proteopy/pl/intensities.py
proteopy/pl/stat_tests.py
proteopy/pl/stats.py
proteopy/pp/__init__.py
proteopy/pp/filtering.py
proteopy/pp/imputation.py
proteopy/pp/normalization.py
proteopy/pp/quantification.py
proteopy/pp/stats.py
proteopy/read/__init__.py
proteopy/read/diann.py
proteopy/read/long.py
proteopy/tl/__init__.py
proteopy/tl/clustering.py
proteopy/tl/copf.py
proteopy/tl/stat_tests.py
proteopy/utils/__init__.py
proteopy/utils/anndata.py
proteopy/utils/array.py
proteopy/utils/copf.py
proteopy/utils/data_structures.py
proteopy/utils/functools.py
proteopy/utils/matplotlib.py
proteopy/utils/pandas.py
proteopy/utils/parsers.py
proteopy/utils/string.py
proteopy-0.1.0.dist-info/licenses/LICENSE
proteopy-0.1.0.dist-info/METADATA
proteopy-0.1.0.dist-info/WHEEL
proteopy-0.1.0.dist-info/top_level.txt
proteopy-0.1.0.dist-info/RECORD
